tocamelcase/__init__.py
tocamelcase-0.0.7.dist-info/METADATA
tocamelcase-0.0.7.dist-info/RECORD
tocamelcase-0.0.7.dist-info/WHEEL
tocamelcase-0.0.7.dist-info/top_level.txt
