Metadata-Version: 2.1
Name: tocamelcase
Version: 0.0.7
Summary: 🐫 To Camel Case: self explanatory!
Home-page: https://abranhe.com
Author: Carlos Abraham
Author-email: abraham@abranhe.com
License: MIT
Project-URL: Source, https://github.com/abranhe/tocamelcase
Platform: UNKNOWN
Classifier: Programming Language :: Python
Classifier: Natural Language :: English
Classifier: Environment :: Plugins
Classifier: Operating System :: OS Independent
Classifier: Intended Audience :: Developers
Classifier: License :: OSI Approved :: MIT License
